Metadata-Version: 2.4
Name: haplohub-cli
Version: 1.0.19
Summary: HaploHub Command Line Interface
Author-email: Mike Polcari <mike@haplotype-labs.com>, Ilya Khrustalev <ilya@haplotype-labs.com>
Requires-Python: >=3.8
Requires-Dist: auth0-python>=4.8.0
Requires-Dist: click>=8.1.8
Requires-Dist: haplohub>=1.0.18
Requires-Dist: pendulum>=3.0.0
Requires-Dist: requests>=2.32.0
Requires-Dist: rich>=13.9.4
